automated_ml_pipeline_framework/framework.py
automated_ml_pipeline_framework-0.0.1.dist-info/LICENCE
automated_ml_pipeline_framework-0.0.1.dist-info/METADATA
automated_ml_pipeline_framework-0.0.1.dist-info/WHEEL
automated_ml_pipeline_framework-0.0.1.dist-info/top_level.txt
automated_ml_pipeline_framework-0.0.1.dist-info/RECORD
