Metadata-Version: 2.1
Name: automated_ml_pipeline_framework
Version: 0.0.1
Summary: Framework for automated machine learning pipeline
Author-email: Aadit Bhargava <bhargavaaadit@gmail.com>
Classifier: Programming Language :: Python :: 3
Classifier: License :: OSI Approved :: MIT License
Classifier: Operating System :: OS Independent
Requires-Python: >=3.8
License-File: LICENCE
